{
  "date": "2026-07-12",
  "updated_at": "2026-07-12T13:21:25.280157+00:00",
  "items": [
    {
      "label": "GMGN",
      "slug": "gmgn",
      "self": true,
      "vol": {
        "d1": 6005842,
        "d7": 239714555,
        "d14": 355867188,
        "d30": 524319339,
        "name": "GMGN"
      },
      "vol_d1_prev": 6005842,
      "vol_d1_chg": null
    },
    {
      "label": "Axiom",
      "slug": "axiom",
      "self": false,
      "vol": {
        "d1": 20469292,
        "d7": 249450278,
        "d14": 600849806,
        "d30": 1109730227,
        "name": "Axiom"
      },
      "vol_d1_prev": 20469292,
      "vol_d1_chg": null
    },
    {
      "label": "Trojan",
      "slug": "trojan",
      "self": false,
      "vol": {
        "d1": 2348219,
        "d7": 25761348,
        "d14": 60049336,
        "d30": 112373204,
        "name": "Trojan"
      },
      "vol_d1_prev": 2348219,
      "vol_d1_chg": null
    },
    {
      "label": "Photon",
      "slug": "photon",
      "self": false,
      "vol": {
        "d1": 594288,
        "d7": 8519418,
        "d14": 21072358,
        "d30": 39123134,
        "name": "Photon"
      },
      "vol_d1_prev": 594288,
      "vol_d1_chg": null
    },
    {
      "label": "BONKbot",
      "slug": "bonkbot",
      "self": false,
      "vol": {
        "d1": 619713,
        "d7": 5109998,
        "d14": 11851096,
        "d30": 19687871,
        "name": "BONKbot"
      },
      "vol_d1_prev": 619713,
      "vol_d1_chg": null
    },
    {
      "label": "Banana Gun",
      "slug": "banana-gun",
      "self": false,
      "vol": {
        "d1": 59891,
        "d7": 15490871,
        "d14": 36659761,
        "d30": 70413170,
        "name": "Banana Gun"
      },
      "vol_d1_prev": 59891,
      "vol_d1_chg": null
    }
  ],
  "users": [
    {
      "label": "Trojan",
      "users_today": 2962,
      "users_7d": 13299,
      "users_14d": 19751,
      "users_30d": 29779,
      "dvol_1d": 1449851.0874208913,
      "dvol_7d": 20345429.699776847,
      "dvol_14d": 47515297.40638516,
      "dvol_30d": 88879838.80419041
    },
    {
      "label": "BONKbot",
      "users_today": 382,
      "users_7d": 2960,
      "users_14d": 4203,
      "users_30d": 6536,
      "dvol_1d": 262204.77365864225,
      "dvol_7d": 5616726.637290355,
      "dvol_14d": 13058678.769223407,
      "dvol_30d": 22644990.57215094
    },
    {
      "label": "Maestro",
      "users_today": 391,
      "users_7d": 2681,
      "users_14d": 4724,
      "users_30d": 17265,
      "dvol_1d": 159345.34709079444,
      "dvol_7d": 5531606.134534024,
      "dvol_14d": 13000423.329613043,
      "dvol_30d": 21556321.023827486
    },
    {
      "label": "Sol Trading Bot",
      "users_today": 180,
      "users_7d": 1190,
      "users_14d": 1968,
      "users_30d": 3097,
      "dvol_1d": 91184.39606063829,
      "dvol_7d": 1450391.0209283347,
      "dvol_14d": 2954796.0030108117,
      "dvol_30d": 5096903.945316389
    },
    {
      "label": "Banana Gun",
      "users_today": 18,
      "users_7d": 236,
      "users_14d": 418,
      "users_30d": 655,
      "dvol_1d": 6526.693699651328,
      "dvol_7d": 63035.63043958421,
      "dvol_14d": 162096.79410770626,
      "dvol_30d": 324088.0502049235
    }
  ]
}